application_example/__init__.py
application_example/example.py
keepcodingtest_oliver-0.1.0.dist-info/METADATA
keepcodingtest_oliver-0.1.0.dist-info/WHEEL
keepcodingtest_oliver-0.1.0.dist-info/top_level.txt
keepcodingtest_oliver-0.1.0.dist-info/RECORD
